ns1/__init__.py
ns1/acls.py
ns1/config.py
ns1/dataset.py
ns1/helpers.py
ns1/monitoring.py
ns1/records.py
ns1/redirect.py
ns1/views.py
ns1/zones.py
ns1/alerting/__init__.py
ns1/alerting/usage_alerts.py
ns1/rest/__init__.py
ns1/rest/account.py
ns1/rest/acls.py
ns1/rest/alerts.py
ns1/rest/apikey.py
ns1/rest/billing_usage.py
ns1/rest/data.py
ns1/rest/datasets.py
ns1/rest/errors.py
ns1/rest/monitoring.py
ns1/rest/permissions.py
ns1/rest/pulsar_decisions.py
ns1/rest/rate_limiting.py
ns1/rest/records.py
ns1/rest/redirect.py
ns1/rest/resource.py
ns1/rest/stats.py
ns1/rest/team.py
ns1/rest/tsig.py
ns1/rest/user.py
ns1/rest/views.py
ns1/rest/zones.py
ns1/rest/transport/__init__.py
ns1/rest/transport/base.py
ns1/rest/transport/basic.py
ns1/rest/transport/requests.py
ns1/rest/transport/twisted.py
ns1_python-0.27.1.dist-info/LICENSE
ns1_python-0.27.1.dist-info/METADATA
ns1_python-0.27.1.dist-info/WHEEL
ns1_python-0.27.1.dist-info/top_level.txt
ns1_python-0.27.1.dist-info/RECORD
