Metadata-Version: 2.1
Name: ns1-python
Version: 0.27.1
Summary: Python SDK for the NS1 DNS platform
Home-page: https://github.com/ns1/ns1-python
Author: NS1 Developers
Author-email: devteam@ns1.com
License: MIT
Keywords: dns development rest sdk ns1 nsone
Platform: UNKNOWN
Classifier: Development Status :: 4 - Beta
Classifier: Intended Audience :: Developers
Classifier: Intended Audience :: Information Technology
Classifier: License :: OSI Approved :: MIT License
Classifier: Operating System :: OS Independent
Classifier: Programming Language :: Python
Classifier: Programming Language :: Python :: 2
Classifier: Programming Language :: Python :: 2.7
Classifier: Programming Language :: Python :: 3
Classifier: Programming Language :: Python :: 3.6
Classifier: Topic :: Software Development :: Libraries :: Python Modules
Classifier: Topic :: Internet :: Name Service (DNS)
